uxaudit/__init__.py
uxaudit/aggregate.py
uxaudit/audit.py
uxaudit/auth.py
uxaudit/browser.py
uxaudit/capture.py
uxaudit/cli.py
uxaudit/config.py
uxaudit/crawler.py
uxaudit/gemini_client.py
uxaudit/prompts.py
uxaudit/redesign.py
uxaudit/report.py
uxaudit/schema.py
uxaudit/utils.py
uxaudit-0.2.0.dist-info/licenses/LICENSE
uxaudit-0.2.0.dist-info/METADATA
uxaudit-0.2.0.dist-info/WHEEL
uxaudit-0.2.0.dist-info/entry_points.txt
uxaudit-0.2.0.dist-info/top_level.txt
uxaudit-0.2.0.dist-info/RECORD
