Metadata-Version: 2.4
Name: uxaudit
Version: 0.2.0
Summary: UX/UI audit tool with screenshots and Gemini analysis
Home-page: https://github.com/albertoburgosplaza/uxaudit
Author-email: Alberto Burgos Plaza <albertoburgosplaza@gmail.com>
License: MIT
Project-URL: Homepage, https://github.com/albertoburgosplaza/uxaudit
Project-URL: Documentation, https://github.com/albertoburgosplaza/uxaudit#readme
Project-URL: Issues, https://github.com/albertoburgosplaza/uxaudit/issues
Project-URL: Changelog, https://github.com/albertoburgosplaza/uxaudit/blob/main/CHANGELOG.md
Project-URL: Source, https://github.com/albertoburgosplaza/uxaudit
Project-URL: CI, https://github.com/albertoburgosplaza/uxaudit/actions/workflows/ci.yml
Keywords: ux,ui,audit,screenshots,gemini,playwright
Classifier: Development Status :: 3 - Alpha
Classifier: Intended Audience :: Developers
Classifier: License :: OSI Approved :: MIT License
Classifier: Programming Language :: Python
Classifier: Programming Language :: Python :: 3
Classifier: Programming Language :: Python :: 3 :: Only
Classifier: Programming Language :: Python :: 3.10
Classifier: Programming Language :: Python :: 3.11
Classifier: Programming Language :: Python :: 3.12
Classifier: Programming Language :: Python :: 3.13
Classifier: Topic :: Software Development :: Quality Assurance
Classifier: Topic :: Software Development :: Testing
Classifier: Topic :: Scientific/Engineering :: Artificial Intelligence
Requires-Python: >=3.10
License-File: LICENSE
Requires-Dist: google-genai>=1.51.0
Requires-Dist: playwright>=1.45.0
Requires-Dist: pydantic>=2.6.0
Requires-Dist: pydantic-settings>=2.2.1
Requires-Dist: typer>=0.12.0
Provides-Extra: dev
Requires-Dist: mypy>=1.8.0; extra == "dev"
Requires-Dist: pytest>=7.4.0; extra == "dev"
Requires-Dist: ruff>=0.4.0; extra == "dev"
Dynamic: license-file
